README.md
setup.cfg
setup.py
pseudo_java/__init__.py
pseudo_java/api_translator.py
pseudo_java/errors.py
pseudo_java/helpers.py
pseudo_java/java_ast_translator.py
pseudo_java/main.py
pseudo_java_df.egg-info/PKG-INFO
pseudo_java_df.egg-info/SOURCES.txt
pseudo_java_df.egg-info/dependency_links.txt
pseudo_java_df.egg-info/entry_points.txt
pseudo_java_df.egg-info/requires.txt
pseudo_java_df.egg-info/top_level.txt