Metadata-Version: 1.1
Name: pseudo-java-df
Version: 0.2.21
Summary: A Java8 compiler to Pseudo
Home-page: https://github.com/dfagneray/pseudo_java
Author: David Fagneray
Author-email: david.fagneray@gmail.com
License: UNKNOWN
Keywords: compiler,generation,c++,ruby,c#,javascript,go,python,pseudo
Platform: UNKNOWN
Classifier: Programming Language :: Python :: 3
Classifier: License :: OSI Approved :: MIT License
Classifier: Operating System :: OS Independent
